essentia/translate.py
essentia/algorithms.py
essentia/_essentia.cpython-310-darwin.so
essentia/standard.py
essentia/plotting.py
essentia/__init__.py
essentia/common.py
essentia/utils.py
essentia/essentia_extractor.py
essentia/progress.py
essentia/streaming.py
essentia/pool.py
essentia/extractor/onsetdetection.py
essentia/extractor/segmentation_max_energy.py
essentia/extractor/sfx.py
essentia/extractor/tempotap.py
essentia/extractor/average_loudness.py
essentia/extractor/scales.py
essentia/extractor/highlevel.py
essentia/extractor/thumbnail.py
essentia/extractor/__init__.py
essentia/extractor/tonal.py
essentia/extractor/panning.py
essentia/extractor/segmentation_bic.py
essentia/extractor/beats.py
essentia/extractor/squeezeInto.py
essentia/extractor/lowlevel.py
essentia/extractor/relativeioi.py
essentia/extractor/segmentation_simple.py
essentia/extractor/chords_dissonance_table.py
essentia/extractor/chords.py
essentia/extractor/segmentation.py
essentia/.dylibs/libtheoraenc.1.dylib
essentia/.dylibs/libsnappy.1.2.2.dylib
essentia/.dylibs/libvorbisenc.2.dylib
essentia/.dylibs/libogg.0.8.6.dylib
essentia/.dylibs/libavutil.54.31.100.dylib
essentia/.dylibs/libgraphite2.3.2.1.dylib
essentia/.dylibs/libpcre2-8.0.dylib
essentia/.dylibs/libx264.164.dylib
essentia/.dylibs/libsamplerate.0.2.2.dylib
essentia/.dylibs/libglib-2.0.0.dylib
essentia/.dylibs/libtheoradec.1.dylib
essentia/.dylibs/libpng16.16.dylib
essentia/.dylibs/libssl.3.dylib
essentia/.dylibs/libmp3lame.0.dylib
essentia/.dylibs/libunibreak.6.dylib
essentia/.dylibs/libfreetype.6.dylib
essentia/.dylibs/libcrypto.3.dylib
essentia/.dylibs/libtensorflow.2.19.0.dylib
essentia/.dylibs/libavformat.56.40.101.dylib
essentia/.dylibs/libfftw3f.3.dylib
essentia/.dylibs/libharfbuzz.0.dylib
essentia/.dylibs/libopencore-amrnb.0.dylib
essentia/.dylibs/libtag.2.1.1.dylib
essentia/.dylibs/libintl.8.dylib
essentia/.dylibs/libfribidi.0.dylib
essentia_tensorflow-2.1b6.dev1389.dist-info/RECORD
essentia_tensorflow-2.1b6.dev1389.dist-info/WHEEL
essentia_tensorflow-2.1b6.dev1389.dist-info/top_level.txt
essentia_tensorflow-2.1b6.dev1389.dist-info/METADATA
essentia_tensorflow-2.1b6.dev1389.dist-info/licenses/COPYING.txt
essentia_tensorflow-2.1b6.dev1389.dist-info/licenses/AUTHORS
