Metadata-Version: 2.4
Name: essentia-tensorflow
Version: 2.1b6.dev1389
Summary: Library for audio and music analysis, description and synthesis, with TensorFlow support
Home-page: http://essentia.upf.edu
Author: Dmitry Bogdanov
Author-email: dmitry.bogdanov@upf.edu
License-Expression: AGPL-3.0-only
Project-URL: Documentation, http://essentia.upf.edu
Project-URL: Source Code, https://github.com/MTG/essentia
Keywords: audio music sound dsp MIR
Platform: any
Classifier: Development Status :: 4 - Beta
Classifier: Intended Audience :: Developers
Classifier: Intended Audience :: Science/Research
Classifier: Topic :: Software Development :: Libraries
Classifier: Topic :: Multimedia :: Sound/Audio :: Analysis
Classifier: Topic :: Multimedia :: Sound/Audio :: Sound Synthesis
Classifier: Operating System :: POSIX
Classifier: Operating System :: MacOS :: MacOS X
Classifier: Programming Language :: C++
Classifier: Programming Language :: Python
Classifier: Programming Language :: Python :: 2
Classifier: Programming Language :: Python :: 3
License-File: COPYING.txt
License-File: AUTHORS
Requires-Dist: numpy>=1.25
Requires-Dist: pyyaml
Requires-Dist: six
Dynamic: author
Dynamic: author-email
Dynamic: classifier
Dynamic: description
Dynamic: home-page
Dynamic: keywords
Dynamic: license-file
Dynamic: platform
Dynamic: project-url
Dynamic: summary
